<?xml version="1.0" encoding="utf-8" ?>
<dwsync>
<file name="Origins.html" server="cis.oaklandcc.edu" local="130935649680000000" remote="130935652700000000" Dst="1" />
<file name="stylee.css" server="cis.oaklandcc.edu" local="130935646920000000" remote="130935652700000000" Dst="1" />
<file name="index.html" server="cis.oaklandcc.edu" local="130935649680000000" remote="130935652700000000" Dst="1" />
<file name="Cost.html" server="cis.oaklandcc.edu" local="130935649660000000" remote="130935652700000000" Dst="1" />
<file name="Cook.html" server="cis.oaklandcc.edu" local="130935649760000000" remote="130935652700000000" Dst="1" />
<file name="styles.css" server="cis.oaklandcc.edu" local="130934852960000000" remote="130935652700000000" Dst="1" />
<file name="Types.html" server="cis.oaklandcc.edu" local="130935651080000000" remote="130935652700000000" Dst="1" />
<file name="WebsitesUsed.txt" server="cis.oaklandcc.edu" local="130934505520000000" remote="130935652700000000" Dst="1" />
<file name="HomePage.html" server="cis.oaklandcc.edu" local="130935543060000000" remote="130935652700000000" Dst="1" />
<file name="stylee - Copy.css" server="cis.oaklandcc.edu" local="130935583040000000" remote="130935652700000000" Dst="1" />
<file name="Origins.html" server="cis.oaklandcc.edu/public_html/" local="130938511680000000" remote="130938512070000000" Dst="1" />
<file name="index.html" server="cis.oaklandcc.edu/public_html/" local="130938513660000000" remote="130938513710000000" Dst="1" />
<file name="Cost.html" server="cis.oaklandcc.edu/public_html/" local="130938511680000000" remote="130938512070000000" Dst="1" />
<file name="Cook.html" server="cis.oaklandcc.edu/public_html/" local="130938511680000000" remote="130938512070000000" Dst="1" />
<file name="styles.css" server="cis.oaklandcc.edu/public_html/" local="130934852960000000" remote="130935663630000000" Dst="1" />
<file name="Types.html" server="cis.oaklandcc.edu/public_html/" local="130938511660000000" remote="130938512080000000" Dst="1" />
<file name="WebsitesUsed.txt" server="cis.oaklandcc.edu/public_html/" local="130937681460000000" remote="130938498550000000" Dst="1" />
<file name="stylee.css" server="cis.oaklandcc.edu/public_html/" local="130938501720000000" remote="130938502000000000" Dst="1" />
<file name="HomePage.html" server="cis.oaklandcc.edu/public_html/" local="130935543060000000" remote="130935663630000000" Dst="1" />
<file name="stylee - Copy.css" server="cis.oaklandcc.edu/public_html/" local="130935583040000000" remote="130935663630000000" Dst="1" />
<file name="Differences.html" server="cis.oaklandcc.edu/public_html/" local="130938511680000000" remote="130938512070000000" Dst="1" />
<file name="Webs.html" server="cis.oaklandcc.edu/public_html/" local="130938511660000000" remote="130938511700000000" Dst="1" />
</dwsync>